kicad_helpers/__init__.py
kicad_helpers/_nbdev.py
kicad_helpers/actions.py
kicad_helpers/test.py
kicad_helpers/utilities.py
kicad_helpers/templates/kitspace.yaml
kicad_helpers/templates/settings.ini
kicad_helpers/templates/.github/workflows/build.yml
kicad_helpers/templates/.kicad_helpers_config/drc.yaml
kicad_helpers/templates/.kicad_helpers_config/erc.yaml
kicad_helpers/templates/.kicad_helpers_config/pcb_pdf.yaml
kicad_helpers/templates/.kicad_helpers_config/pcb_svg.yaml
kicad_helpers/templates/.kicad_helpers_config/sch_pdf.yaml
kicad_helpers/templates/.kicad_helpers_config/sch_svg.yaml
kicad_helpers/templates/.kicad_helpers_config/manufacturers/PCBWay.yaml
kicad_helpers/templates/.kicad_helpers_config/manufacturers/default.yaml
kicad_helpers/templates/tests/Tests.ipynb
kicad_helpers-0.14.dist-info/LICENSE.md
kicad_helpers-0.14.dist-info/METADATA
kicad_helpers-0.14.dist-info/WHEEL
kicad_helpers-0.14.dist-info/entry_points.txt
kicad_helpers-0.14.dist-info/top_level.txt
kicad_helpers-0.14.dist-info/RECORD
