Metadata-Version: 2.1
Name: kicad-helpers
Version: 0.14
Summary: Scripts, templates, and examples for managing KiCad projects.
Home-page: https://github.com/ryanfobel/kicad-helpers/tree/main/
Author: Ryan Fobel
Author-email: ryan@fobel.net
License: BSD License
Keywords: kicad continuous-integration
Platform: UNKNOWN
Classifier: Development Status :: 3 - Alpha
Classifier: Intended Audience :: Developers
Classifier: Natural Language :: English
Classifier: Programming Language :: Python :: 3.6
Classifier: Programming Language :: Python :: 3.7
Classifier: Programming Language :: Python :: 3.8
Classifier: License :: OSI Approved :: BSD License
Requires-Python: >=3.6
Requires-Dist: fastcore (>=1.3.19)
Requires-Dist: nbformat (>=4.4.0)
Requires-Dist: nbconvert (<6)
Requires-Dist: pyyaml
Requires-Dist: jupyter-client
Requires-Dist: jupyter
Requires-Dist: ipykernel
Requires-Dist: ghapi
Requires-Dist: fastrelease
Requires-Dist: gitpython
Requires-Dist: pandas
Requires-Dist: python-dotenv
Requires-Dist: nbdev
Requires-Dist: pandera
Requires-Dist: kifield
